prefix_list_agent/__init__.py
prefix_list_agent/__meta__.py
prefix_list_agent/agent.py
prefix_list_agent/base.py
prefix_list_agent/cli.py
prefix_list_agent/exceptions.py
prefix_list_agent/worker.py
prefix_list_agent-0.1.1.data/scripts/PrefixListAgent
prefix_list_agent-0.1.1.dist-info/LICENSE
prefix_list_agent-0.1.1.dist-info/METADATA
prefix_list_agent-0.1.1.dist-info/WHEEL
prefix_list_agent-0.1.1.dist-info/top_level.txt
prefix_list_agent-0.1.1.dist-info/RECORD
