Metadata-Version: 2.1
Name: prefix-list-agent
Version: 0.1.1
Summary: An EOS agent to dynamically update IRR based prefix-lists
Home-page: https://github.com/wolcomm/eos-prefix-list-agent
Author: Ben Maddison
Author-email: benm@workonline.africa
License: MIT
Download-URL: https://github.com/wolcomm/eos-prefix-list-agent/0.1.1
Platform: UNKNOWN
Classifier: Development Status :: 4 - Beta
Classifier: Environment :: Other Environment
Classifier: Intended Audience :: Telecommunications Industry
Classifier: License :: OSI Approved :: MIT License
Classifier: Operating System :: POSIX :: Other
Classifier: Programming Language :: Python :: 2.7
Classifier: Topic :: Internet
Classifier: Topic :: System :: Networking
